dropme/__init__.py
dropme/app.py
dropme/client.py
dropme/error.py
dropme/settings.yaml
dropme/commands/__init__.py
dropme/commands/account.py
dropme/commands/base.py
dropme/commands/files.py
dropme/commands/folder.py
dropme/common/__init__.py
dropme/common/utils.py
dropme-1.1.0.dist-info/DESCRIPTION.rst
dropme-1.1.0.dist-info/METADATA
dropme-1.1.0.dist-info/RECORD
dropme-1.1.0.dist-info/WHEEL
dropme-1.1.0.dist-info/entry_points.txt
dropme-1.1.0.dist-info/metadata.json
dropme-1.1.0.dist-info/top_level.txt
tests/unit/__init__.py
tests/unit/test_client.py
tests/unit/cli/__init__.py
tests/unit/cli/test_account.py
tests/unit/cli/test_engine.py
tests/unit/cli/test_files.py
tests/unit/cli/test_folder.py
tests/unit/common/__init__.py
tests/unit/common/test_utils.py
