Metadata-Version: 2.0
Name: dropme
Version: 1.1.0
Summary: CLI tool for managing Dropbox environment.
Home-page: https://github.com/tivaliy/dropme
Author: Vitalii Kulanov
Author-email: vitaliy@kulanov.org.ua
License: MIT
Keywords: CLI Dropbox
Platform: UNKNOWN
Classifier: Development Status :: 5 - Production/Stable
Classifier: Environment :: Console
Classifier: Intended Audience :: Information Technology
Classifier: License :: OSI Approved :: MIT License
Classifier: Operating System :: POSIX :: Linux
Classifier: Programming Language :: Python
Classifier: Programming Language :: Python :: 3
Classifier: Programming Language :: Python :: 3.5
Classifier: Programming Language :: Python :: 3.6
Classifier: Topic :: Communications :: File Sharing
Requires-Dist: PyYAML (>=3.1.0)
Requires-Dist: cliff (>=2.9.0)
Requires-Dist: dropbox (>=8.5.0)
